{"is_source_file": true, "format": "JavaScript (React JSX)", "description": "This file initializes a React application, rendering the main <App /> component into the DOM element with id 'root' using ReactDOM's createRoot method. It sets up the rendering environment with strict mode enabled.", "external_files": ["react", "react-dom/client", "./index.css", "./App"], "external_methods": ["ReactDOM.createRoot", "root.render"], "published": [], "classes": [], "methods": [{"name": "render", "description": "Renders the <App /> component within React.StrictMode into the DOM."}], "calls": ["ReactDOM.createRoot", "root.render"], "search-terms": ["React", "ReactDOM", "index.js", "render", "App", "React StrictMode"], "state": 2, "file_id": 6, "knowledge_revision": 28, "git_revision": "20faf71ab2e2621cfcb2e88e04f2ea904b454d15", "revision_history": [{"24": "20faf71ab2e2621cfcb2e88e04f2ea904b454d15"}, {"28": "20faf71ab2e2621cfcb2e88e04f2ea904b454d15"}], "ctags": [{"_type": "tag", "name": "root", "path": "/home/kavia/workspace/code-generation/pronet-connect-127616-127625/members_connect_frontend/src/index.js", "pattern": "/^const root = ReactDOM.createRoot(document.getElementById(\"root\"));$/", "language": "JavaScript", "kind": "constant"}], "hash": "d1bec410650d3e4df6e34133a7a0a82c", "format-version": 4, "code-base-name": "members_connect_frontend", "filename": "members_connect_frontend/src/index.js"}